scriptaxstd/__init__.py
scriptaxstd/main.py
scriptaxstd/drivers/Driver.py
scriptaxstd/drivers/__init__.py
scriptaxstd/drivers/driver.py
scriptaxstd/drivers/builtin/Api.py
scriptaxstd/drivers/builtin/ApiXml.py
scriptaxstd/drivers/builtin/StandardLibrary.py
scriptaxstd/drivers/builtin/__init__.py
scriptaxstd/flow/Binary.py
scriptaxstd/flow/Delegator.py
scriptaxstd/flow/File.py
scriptaxstd/flow/Json.py
scriptaxstd/flow/Map.py
scriptaxstd/flow/Math.py
scriptaxstd/flow/Path.py
scriptaxstd/flow/Restapi.py
scriptaxstd/flow/String.py
scriptaxstd/flow/Time.py
scriptaxstd/flow/__init__.py
scriptaxstd/scriptax/Binary.ah
scriptaxstd/scriptax/File.ah
scriptaxstd/scriptax/Json.ah
scriptaxstd/scriptax/Map.ah
scriptaxstd/scriptax/Math.ah
scriptaxstd/scriptax/Path.ah
scriptaxstd/scriptax/Restapi.ah
scriptaxstd/scriptax/String.ah
scriptaxstd/scriptax/Time.ah
scriptaxstd/scriptax/test.ah
scriptaxstd/tests/DriverTest.py
scriptaxstd/tests/__init__.py
scriptaxstd-0.0.13.dist-info/LICENSE
scriptaxstd-0.0.13.dist-info/METADATA
scriptaxstd-0.0.13.dist-info/WHEEL
scriptaxstd-0.0.13.dist-info/top_level.txt
scriptaxstd-0.0.13.dist-info/RECORD
