Metadata-Version: 2.1
Name: scriptaxstd
Version: 0.0.13
Summary: The Standard Library is a driver which provides lots of additional functionality to complement the Scriptax driver.
Home-page: https://github.com/Apitax/StandardLibrary
Author: Shawn Clake
Author-email: shawn.clake@gmail.com
License: UNKNOWN
Keywords: restful,api,commandtax,scriptax,apitax,drivers,plugins
Platform: UNKNOWN
Classifier: Programming Language :: Python :: 3
Classifier: Operating System :: OS Independent
Requires-Dist: apitaxcore (==3.0.9)
Requires-Dist: click
Requires-Dist: commandtax (==0.0.8)
Requires-Dist: scriptax (==4.0.1)
